m2h_ai/__init__.py
m2h_ai/cli.py
m2h_ai/core.py
m2h_ai/update.py
m2h_ai-1.0.3.dist-info/METADATA
m2h_ai-1.0.3.dist-info/WHEEL
m2h_ai-1.0.3.dist-info/entry_points.txt
m2h_ai-1.0.3.dist-info/top_level.txt
m2h_ai-1.0.3.dist-info/RECORD
