Metadata-Version: 2.4
Name: m2h-ai
Version: 1.0.3
Summary: Professional CLI AI by M2H Web Solution
Author: M2H Web Solution
Requires-Python: >=3.8
Requires-Dist: requests
Requires-Dist: colorama
Requires-Dist: packaging
